{
  "id": "cmdpatch",
  "timestamp": 1598574218.0,
  "versions": [
    {
      "timestamp": 1598574218.0,
      "version": "v1.0",
      "versionCode": 1,
      "zipUrl": "https://magisk-modules-alt-repo.github.io/json-v2/modules/cmdpatch/v1.0_1.zip",
      "changelog": ""
    },
    {
      "timestamp": 1598574218.0,
      "version": "1.1.5",
      "versionCode": 7,
      "zipUrl": "https://magisk-modules-alt-repo.github.io/json-v2/modules/cmdpatch/1.1.5_7.zip",
      "changelog": "",
      "size": 16024
    },
    {
      "timestamp": 1598574218.0,
      "version": "1.2.1",
      "versionCode": 9,
      "zipUrl": "https://magisk-modules-alt-repo.github.io/json-v2/modules/cmdpatch/1.2.1_9.zip",
      "changelog": "",
      "size": 16024
    }
  ]
}